{"frames":{"wall-grey-vertical":{"frame":{"x":2,"y":2,"w":32,"h":32},"rotated":false,"trimmed":false,"spriteSourceSize":{"x":0,"y":0,"w":32,"h":32},"sourceSize":{"w":32,"h":32}},"wall-grey-vertical-cap-top":{"frame":{"x":36,"y":2,"w":32,"h":32},"rotated":false,"trimmed":false,"spriteSourceSize":{"x":0,"y":0,"w":32,"h":32},"sourceSize":{"w":32,"h":32}},"wall-grey-vertical-cap-bottom":{"frame":{"x":2,"y":36,"w":32,"h":32},"rotated":false,"trimmed":false,"spriteSourceSize":{"x":0,"y":0,"w":32,"h":32},"sourceSize":{"w":32,"h":32}},"wall-grey-t-junction-top":{"frame":{"x":36,"y":36,"w":32,"h":32},"rotated":false,"trimmed":false,"spriteSourceSize":{"x":0,"y":0,"w":32,"h":32},"sourceSize":{"w":32,"h":32}},"wall-grey-t-junction-right":{"frame":{"x":70,"y":2,"w":32,"h":32},"rotated":false,"trimmed":false,"spriteSourceSize":{"x":0,"y":0,"w":32,"h":32},"sourceSize":{"w":32,"h":32}},"wall-grey-t-junction-left":{"frame":{"x":70,"y":36,"w":32,"h":32},"rotated":false,"trimmed":false,"spriteSourceSize":{"x":0,"y":0,"w":32,"h":32},"sourceSize":{"w":32,"h":32}},"wall-grey-t-junction-bottom":{"frame":{"x":2,"y":70,"w":32,"h":32},"rotated":false,"trimmed":false,"spriteSourceSize":{"x":0,"y":0,"w":32,"h":32},"sourceSize":{"w":32,"h":32}},"wall-grey-standalone":{"frame":{"x":36,"y":70,"w":32,"h":32},"rotated":false,"trimmed":false,"spriteSourceSize":{"x":0,"y":0,"w":32,"h":32},"sourceSize":{"w":32,"h":32}},"wall-grey-horizontal":{"frame":{"x":70,"y":70,"w":32,"h":32},"rotated":false,"trimmed":false,"spriteSourceSize":{"x":0,"y":0,"w":32,"h":32},"sourceSize":{"w":32,"h":32}},"wall-grey-horizontal-cap-right":{"frame":{"x":104,"y":2,"w":32,"h":32},"rotated":false,"trimmed":false,"spriteSourceSize":{"x":0,"y":0,"w":32,"h":32},"sourceSize":{"w":32,"h":32}},"wall-grey-horizontal-cap-left":{"frame":{"x":104,"y":36,"w":32,"h":32},"rotated":false,"trimmed":false,"spriteSourceSize":{"x":0,"y":0,"w":32,"h":32},"sourceSize":{"w":32,"h":32}},"wall-grey-corner-top-right":{"frame":{"x":104,"y":70,"w":32,"h":32},"rotated":false,"trimmed":false,"spriteSourceSize":{"x":0,"y":0,"w":32,"h":32},"sourceSize":{"w":32,"h":32}},"wall-grey-corner-top-left":{"frame":{"x":2,"y":104,"w":32,"h":32},"rotated":false,"trimmed":false,"spriteSourceSize":{"x":0,"y":0,"w":32,"h":32},"sourceSize":{"w":32,"h":32}},"wall-grey-corner-bottom-right":{"frame":{"x":36,"y":104,"w":32,"h":32},"rotated":false,"trimmed":false,"spriteSourceSize":{"x":0,"y":0,"w":32,"h":32},"sourceSize":{"w":32,"h":32}},"wall-grey-corner-bottom-left":{"frame":{"x":70,"y":104,"w":32,"h":32},"rotated":false,"trimmed":false,"spriteSourceSize":{"x":0,"y":0,"w":32,"h":32},"sourceSize":{"w":32,"h":32}},"wall-grey-centre":{"frame":{"x":104,"y":104,"w":32,"h":32},"rotated":false,"trimmed":false,"spriteSourceSize":{"x":0,"y":0,"w":32,"h":32},"sourceSize":{"w":32,"h":32}},"floor-grey-decoration-hole":{"frame":{"x":138,"y":2,"w":32,"h":32},"rotated":false,"trimmed":false,"spriteSourceSize":{"x":0,"y":0,"w":32,"h":32},"sourceSize":{"w":32,"h":32}},"floor-grey-decoration-grate-3":{"frame":{"x":138,"y":36,"w":32,"h":32},"rotated":false,"trimmed":false,"spriteSourceSize":{"x":0,"y":0,"w":32,"h":32},"sourceSize":{"w":32,"h":32}},"floor-grey-decoration-grate-2":{"frame":{"x":138,"y":70,"w":32,"h":32},"rotated":false,"trimmed":false,"spriteSourceSize":{"x":0,"y":0,"w":32,"h":32},"sourceSize":{"w":32,"h":32}},"floor-grey-decoration-grate-1":{"frame":{"x":138,"y":104,"w":32,"h":32},"rotated":false,"trimmed":false,"spriteSourceSize":{"x":0,"y":0,"w":32,"h":32},"sourceSize":{"w":32,"h":32}},"floor-grey-3":{"frame":{"x":2,"y":138,"w":32,"h":32},"rotated":false,"trimmed":false,"spriteSourceSize":{"x":0,"y":0,"w":32,"h":32},"sourceSize":{"w":32,"h":32}},"floor-grey-2":{"frame":{"x":36,"y":138,"w":32,"h":32},"rotated":false,"trimmed":false,"spriteSourceSize":{"x":0,"y":0,"w":32,"h":32},"sourceSize":{"w":32,"h":32}},"floor-grey-1":{"frame":{"x":70,"y":138,"w":32,"h":32},"rotated":false,"trimmed":false,"spriteSourceSize":{"x":0,"y":0,"w":32,"h":32},"sourceSize":{"w":32,"h":32}},"floor-grey-0":{"frame":{"x":104,"y":138,"w":32,"h":32},"rotated":false,"trimmed":false,"spriteSourceSize":{"x":0,"y":0,"w":32,"h":32},"sourceSize":{"w":32,"h":32}},"decoration-screen-0":{"frame":{"x":138,"y":138,"w":17,"h":26},"rotated":false,"trimmed":true,"spriteSourceSize":{"x":7,"y":3,"w":17,"h":26},"sourceSize":{"w":32,"h":32}},"decoration-light-red":{"frame":{"x":172,"y":2,"w":20,"h":30},"rotated":false,"trimmed":true,"spriteSourceSize":{"x":5,"y":0,"w":20,"h":30},"sourceSize":{"w":32,"h":32}},"decoration-light-green":{"frame":{"x":172,"y":34,"w":20,"h":30},"rotated":false,"trimmed":true,"spriteSourceSize":{"x":5,"y":0,"w":20,"h":30},"sourceSize":{"w":32,"h":32}}},"meta":{"app":"http://github.com/pixijs/assetpack","version":"1.0","image":"ship-map-sbeUlQ@0.5x.png","format":"RGBA8888","size":{"w":194,"h":172},"scale":0.5,"related_multi_packs":[]}}